Metadata-Version: 2.1
Name: chain-pymysql
Version: 1.0.6
Summary: Easy to use PyMySQL.
Home-page: https://github.com/Tiacx/chain-pymysql
Author: Taic
Project-URL: Documentation, https://github.com/Tiacx/chain-pymysql
Keywords: ChainPyMySql
Classifier: Development Status :: 5 - Production/Stable
Classifier: Programming Language :: Python :: 3
Classifier: Programming Language :: Python :: 3.6
Classifier: Programming Language :: Python :: 3.7
Classifier: Programming Language :: Python :: 3.8
Classifier: Programming Language :: Python :: 3.9
Classifier: Programming Language :: Python :: 3.10
Classifier: Programming Language :: Python :: 3.11
Classifier: Intended Audience :: Developers
Classifier: License :: OSI Approved :: MIT License
Classifier: Topic :: Database
License-File: LICENSE.txt
